sprof/__init__.py
sprof/api.py
sprof/console.py
sprof/exceptions.py
sprof/utils.py
sprof/version.py
sprof/core/__init__.py
sprof/core/info.py
sprof/core/init.py
sprof/core/meta.py
sprof/data/project_template/.gitignore
sprof/data/project_template/a010_first_script.py
sprof/data/project_template/environment.yml
sprof/data/project_template/local.py
sprof/data/project_template/utils.py
sprof/data/project_template/inputs/.gitinclude
sprof/data/spf_example/a010_clean_data.py
sprof/data/spf_example/a020_calculate.py
sprof/data/spf_example/a030_visualize.py
sprof/data/spf_example/environment.yml
sprof/data/spf_example/local.py
sprof/data/spf_example/utils.py
sprof/data/spf_example/inputs/bingham_earthquakes.csv
sprof-0.0.2.dist-info/LICENSE
sprof-0.0.2.dist-info/METADATA
sprof-0.0.2.dist-info/WHEEL
sprof-0.0.2.dist-info/entry_points.txt
sprof-0.0.2.dist-info/top_level.txt
sprof-0.0.2.dist-info/RECORD
