Metadata-Version: 2.1
Name: sprof
Version: 0.0.2
Summary: A simple project framework to keep you from getting burned
Download-URL: https://pypi.python.org/pypi/sprof
Author: Derrick Chambers
Author-email: Derrick Chambers <chambers.ja.derrick@gmail.com>
License: MIT License
Project-URL: Bug Tracker, https://github.com/d-chambers/sprof/issues
Project-URL: Documentation, https://github.com/d-chambers/sprof
Project-URL: Homepage, https://github.com/d-chambers/sprof
Keywords: workflow,projects
Classifier: Development Status :: 4 - Beta
Classifier: License :: OSI Approved :: MIT License
Classifier: Programming Language :: Python :: 3.9
Classifier: Programming Language :: Python :: 3.10
Classifier: Programming Language :: Python :: 3.11
Classifier: Topic :: Scientific/Engineering
Requires-Python: >=3.9
License-File: LICENSE
Requires-Dist: doit
Requires-Dist: typer
Requires-Dist: rich
Requires-Dist: jinja2
Provides-Extra: dev
Requires-Dist: sprof[test] ; extra == 'dev'
Provides-Extra: docs
Requires-Dist: sphinx (>=1.5.1) ; extra == 'docs'
Requires-Dist: ipykernel ; extra == 'docs'
Requires-Dist: numpydoc ; extra == 'docs'
Requires-Dist: sphinx-autodoc-typehints ; extra == 'docs'
Requires-Dist: pandoc ; extra == 'docs'
Requires-Dist: recommonmark ; extra == 'docs'
Requires-Dist: jupytext ; extra == 'docs'
Requires-Dist: nbsphinx ; extra == 'docs'
Provides-Extra: test
Requires-Dist: pytest ; extra == 'test'
Requires-Dist: pre-commit ; extra == 'test'
Requires-Dist: scikit-learn ; extra == 'test'
